{"chunk_definitions":[{"row":45,"row_count":1,"visible":true,"expansion_state":0,"options":{"engine":"r","label":"unnamed-chunk-23"},"document_id":"CE02E268","chunk_id":"cmoofjhbo29np","chunk_label":"unnamed-chunk-1"},{"row":54,"row_count":1,"visible":true,"expansion_state":0,"options":{"engine":"r","label":"unnamed-chunk-24"},"document_id":"CE02E268","chunk_id":"cyy1p3c9zzj6a","chunk_label":"unnamed-chunk-2"},{"row":64,"row_count":1,"visible":true,"expansion_state":0,"options":{"engine":"r","label":"unnamed-chunk-25"},"document_id":"CE02E268","chunk_id":"cesv26m4k4zih","chunk_label":"unnamed-chunk-3"},{"row":76,"row_count":1,"visible":true,"expansion_state":0,"options":{"engine":"r","label":"unnamed-chunk-26"},"document_id":"CE02E268","chunk_id":"c3yxpaw085qt4","chunk_label":"unnamed-chunk-4"},{"row":83,"row_count":1,"visible":true,"expansion_state":0,"options":{"engine":"r","label":"unnamed-chunk-27"},"document_id":"CE02E268","chunk_id":"c8pwd9smh6m4b","chunk_label":"unnamed-chunk-5"},{"row":91,"row_count":1,"visible":true,"expansion_state":0,"options":{"engine":"r","label":"unnamed-chunk-28"},"document_id":"CE02E268","chunk_id":"c0vt6wmocr5fl","chunk_label":"unnamed-chunk-6"},{"row":98,"row_count":1,"visible":true,"expansion_state":0,"options":{"engine":"r","label":"unnamed-chunk-29"},"document_id":"CE02E268","chunk_id":"c97r9xnjphpfw","chunk_label":"unnamed-chunk-7"},{"row":115,"row_count":1,"visible":true,"expansion_state":0,"options":{"engine":"r","label":"unnamed-chunk-30"},"document_id":"CE02E268","chunk_id":"c9a9hwsk53r74","chunk_label":"unnamed-chunk-8"},{"row":126,"row_count":1,"visible":true,"expansion_state":0,"options":{"engine":"r","label":"unnamed-chunk-31"},"document_id":"CE02E268","chunk_id":"cq1za1r2w4f9i","chunk_label":"unnamed-chunk-9"},{"row":141,"row_count":1,"visible":true,"expansion_state":0,"options":{"engine":"r","label":"unnamed-chunk-32"},"document_id":"CE02E268","chunk_id":"cjbyz0qnf50ey","chunk_label":"unnamed-chunk-10"},{"row":149,"row_count":1,"visible":true,"expansion_state":0,"options":{"engine":"r","label":"unnamed-chunk-36"},"document_id":"CE02E268","chunk_id":"chuyp9ygew974","chunk_label":"unnamed-chunk-11"},{"row":165,"row_count":1,"visible":true,"expansion_state":0,"options":{"engine":"r","label":"unnamed-chunk-41"},"document_id":"CE02E268","chunk_id":"cyfw9h79ofrwd","chunk_label":"unnamed-chunk-13"},{"row":171,"row_count":1,"visible":true,"expansion_state":0,"options":{"engine":"r","label":"unnamed-chunk-42"},"document_id":"CE02E268","chunk_id":"cema5gg80dbl2","chunk_label":"unnamed-chunk-14"},{"row":179,"row_count":1,"visible":true,"expansion_state":0,"options":{"engine":"r","label":"unnamed-chunk-43"},"document_id":"CE02E268","chunk_id":"cayvmbr6yx13k","chunk_label":"unnamed-chunk-15"},{"row":187,"row_count":1,"visible":true,"expansion_state":0,"options":{"engine":"r","label":"unnamed-chunk-44"},"document_id":"CE02E268","chunk_id":"c9y040kurrvab","chunk_label":"unnamed-chunk-16"},{"row":196,"row_count":1,"visible":true,"expansion_state":0,"options":{"engine":"r","label":"unnamed-chunk-48"},"document_id":"CE02E268","chunk_id":"cc76rks012i0z","chunk_label":"unnamed-chunk-17"}],"doc_write_time":1670436328,"chunk_rendered_width":550}